pykit/__init__.py
pykit/cls.py
pykit/condition/__init__.py
pykit/condition/_mark.py
pykit/condition/errors.py
pykit/condition/test_main.py
pykit/conftest.py
pykit/crypto.py
pykit/dt.py
pykit/env.py
pykit/errors/__init__.py
pykit/errors/_internals.py
pykit/errors/expect.py
pykit/errors/main.py
pykit/errors/test_expect.py
pykit/expectation/__init__.py
pykit/expectation/errors.py
pykit/expectation/test_list.py
pykit/expectation/utils.py
pykit/fmt/__init__.py
pykit/fmt/test_utils.py
pykit/func.py
pykit/map/__init__.py
pykit/map/test_main.py
pykit/never.py
pykit/rnd/__init__.py
pykit/rnd/test_main.py
pykit/search.py
pykit/str.py
pykit/test_cls.py
pykit/test_env.py
pykit/types.py
pykit/validation/__init__.py
pykit/validation/errors.py
pykit/validation/validator.py
pykit/yml.py
sbpykit-0.4.12.dist-info/LICENSE
sbpykit-0.4.12.dist-info/METADATA
sbpykit-0.4.12.dist-info/WHEEL
sbpykit-0.4.12.dist-info/RECORD
