Metadata-Version: 2.1
Name: sbpykit
Version: 0.4.12
Summary: Python toolkit.
License: MIT
Author: ryzhovalex
Author-email: thed4rkof@gmail.com
Requires-Python: >=3.11,<4.0
Classifier: License :: OSI Approved :: MIT License
Classifier: Programming Language :: Python :: 3
Classifier: Programming Language :: Python :: 3.11
Requires-Dist: bcrypt (>=4.1.1,<5.0.0)
Requires-Dist: dictdiffer (>=0.9.0,<0.10.0)
Requires-Dist: pydantic (>=2.5.2,<3.0.0)
Requires-Dist: python-benedict (>=0.33.0,<0.34.0)
Requires-Dist: pyyaml (>=6.0.1,<7.0.0)
